Workbook

Sheet Executive_Summary
A1: DEXCOM EMEA COMMERCIAL PRICING & MARGIN ANALYTICS ENGINE
A2: Executive Decision Model: Salesforce Price Book Synchronization, Gross-to-Net Optimization & Multi-Market Parity
A4: Model Governance & Versioning | D4: EMEA COMMERCIAL PRICING SCORECARD (ANNUALIZED)
A5: Lead Analyst: | B5: Debbrata Kumar Adhikary (Vilnius Commercial Analytics) | D5: Blended Net Realized ASP | E5: Gross-to-Net Realization | F5: Blended Contribution Margin | G5: Jira IT Sync Compliance
A6: Target Entity: | B6: Dexcom EMEA Commercial Distribution & Direct-to-Consumer | D6: =AVERAGE(Gross_to_Net_Waterfall!I5:I14) | E6: =(AVERAGE(Gross_to_Net_Waterfall!I5:I14)/AVERAGE(Gross_to_Net_Waterfall!C5:C14)) | F6: =AVERAGE(Gross_to_Net_Waterfall!L5:L14) | G6: 100.0%
A7: Primary Systems: | B7: Salesforce SFDC CPQ, Jira Agile, SAP/NetSuite ERP | D7: Weighted Net Price | E7: Margin Retention Rate | F7: Post-COGS Net Margin | G7: Active SFDC Deployment
A8: Currencies Modeled: | B8: EUR (Base), GBP (1.17 EUR), SEK (0.086 EUR), DKK (0.134 EUR)
A9: Model Status: | B9: Active Production (Synced with SFDC Price Book Q4 release)
A12: EXECUTIVE SCENARIO ANALYSIS (MACRO PRICING DECISION SIMULATION)
A13: Scenario Name | B13: Strategic Rationale | C13: Price Adj % | D13: Volume Elasticity | E13: EMEA Revenue (€M) | F13: Gross Profit (€M) | G13: Net Margin %
A14: Base Case (Q4 Approved) | B14: Current SFDC Price Book catalog across EMEA channels | C14: 0 | D14: -1.35 | E14: 48.5 | F14: 31.52 | G14: 0.65
A15: Scenario 1: Inflationary Indexation | B15: Pass-through of 4.5% CPI across D2C + 3.0% on Distributors | C15: 0.038 | D15: -1.35 | E15: 50.12 | F15: 33.08 | G15: 0.66
A16: Scenario 2: Tier-1 Volume Concession | B16: Grant additional 3.5% discount for Tier-1 distributors pledging +15% volume | C16: -0.035 | D16: -1.55 | E16: 52.4 | F16: 32.8 | G16: 0.626
A17: Scenario 3: Nordics FX Defense | B17: Hedge SEK/DKK depreciation with +6% local list price adjustment | C17: 0.06 | D17: -1.1 | E17: 49.3 | F17: 32.4 | G17: 0.657

Sheet Price_Book_Master
A1: SALESFORCE (SFDC) EMEA PRICE BOOK MASTER REPOSITORY
A2: Master SKU Catalog, Multi-Currency FX Conversions, Channel Tiering & Jira Deployment Tickets
A4: SKU Code | B4: Product Description | C4: Market / Region | D4: Channel | E4: Currency | F4: List Price (Local) | G4: FX to EUR | H4: List Price (EUR) | I4: Distributor Disc % | J4: Contracted Price (EUR) | K4: SFDC PriceBook ID | L4: Jira Ticket ID | M4: IT Status
A5: DX-CGM-G7-SEN-01 | B5: Dexcom G7 Continuous Glucose Sensor (1 pk) | C5: Germany (DE) | D5: Distributor (Tier 1) | E5: EUR | F5: 68.5 | G5: 1 | H5: =F5*G5 | I5: 0.32 | J5: =H5*(1-I5) | K5: 01s5G000004XYZ1 | L5: JIRA-PRC-1042 | M5: Deployed
A6: DX-CGM-G7-SEN-01 | B6: Dexcom G7 Continuous Glucose Sensor (1 pk) | C6: Germany (DE) | D6: Direct-to-Consumer (D2C) | E6: EUR | F6: 72 | G6: 1 | H6: =F6*G6 | I6: 0 | J6: =H6*(1-I6) | K6: 01s5G000004XYZ2 | L6: JIRA-PRC-1042 | M6: Deployed
A7: DX-CGM-G7-SEN-01 | B7: Dexcom G7 Continuous Glucose Sensor (1 pk) | C7: United Kingdom (UK) | D7: Distributor (Tier 1) | E7: GBP | F7: 58 | G7: 1.17 | H7: =F7*G7 | I7: 0.3 | J7: =H7*(1-I7) | K7: 01s5G000004XYZ3 | L7: JIRA-PRC-1045 | M7: Deployed
A8: DX-CGM-G7-SEN-01 | B8: Dexcom G7 Continuous Glucose Sensor (1 pk) | C8: France (FR) | D8: Hospital / Tender | E8: EUR | F8: 64 | G8: 1 | H8: =F8*G8 | I8: 0.28 | J8: =H8*(1-I8) | K8: 01s5G000004XYZ4 | L8: JIRA-PRC-1048 | M8: Deployed
A9: DX-CGM-G7-SEN-01 | B9: Dexcom G7 Continuous Glucose Sensor (1 pk) | C9: Sweden (SE) | D9: Distributor (Tier 2) | E9: SEK | F9: 790 | G9: 0.086 | H9: =F9*G9 | I9: 0.25 | J9: =H9*(1-I9) | K9: 01s5G000004XYZ5 | L9: JIRA-PRC-1050 | M9: Deployed
A10: DX-CGM-G7-SEN-01 | B10: Dexcom G7 Continuous Glucose Sensor (1 pk) | C10: Baltics (LT/LV/EE) | D10: Authorized Distributor | E10: EUR | F10: 66 | G10: 1 | H10: =F10*G10 | I10: 0.3 | J10: =H10*(1-I10) | K10: 01s5G000004XYZ6 | L10: JIRA-PRC-1052 | M10: Deployed
A11: DX-CGM-G7-TRN-01 | B11: Dexcom G7 Rechargeable Transmitter | C11: Germany (DE) | D11: Distributor (Tier 1) | E11: EUR | F11: 145 | G11: 1 | H11: =F11*G11 | I11: 0.35 | J11: =H11*(1-I11) | K11: 01s5G000004TRN1 | L11: JIRA-PRC-1055 | M11: Deployed
A12: DX-CGM-G7-TRN-01 | B12: Dexcom G7 Rechargeable Transmitter | C12: United Kingdom (UK) | D12: Direct-to-Consumer (D2C) | E12: GBP | F12: 125 | G12: 1.17 | H12: =F12*G12 | I12: 0 | J12: =H12*(1-I12) | K12: 01s5G000004TRN2 | L12: JIRA-PRC-1055 | M12: Deployed
A13: DX-CGM-G6-SEN-03 | B13: Dexcom G6 Legacy Sensor Pack (3 pk) | C13: France (FR) | D13: Distributor (Tier 1) | E13: EUR | F13: 175 | G13: 1 | H13: =F13*G13 | I13: 0.34 | J13: =H13*(1-I13) | K13: 01s5G000004LEG1 | L13: JIRA-PRC-1060 | M13: Deployed
A14: DX-CGM-APP-SUB-01 | B14: Dexcom Clarity Clinical Enterprise Sub | C14: EMEA Regional | D14: Direct-to-Clinic | E14: EUR | F14: 350 | G14: 1 | H14: =F14*G14 | I14: 0.15 | J14: =H14*(1-I14) | K14: 01s5G000004SUB1 | L14: JIRA-PRC-1062 | M14: Deployed

Sheet Gross_to_Net_Waterfall
A1: GROSS-TO-NET COMMERCIAL MARGIN WATERFALL (EMEA DISTRIBUTORS & D2C)
A2: Deduction Bridges: Contractual Discounts, Growth Rebates, Co-Marketing, Cash Terms & Net Realized Contribution
A4: SKU Code | B4: Market / Account | C4: Gross List (€) | D4: Base Disc (€) | E4: Volume Rebate (€) | F4: Co-Op MDF (€) | G4: Cash Terms (€) | H4: Logistics (€) | I4: Net Realized ASP (€) | J4: Direct COGS (€) | K4: Net Margin (€) | L4: Net Margin % | M4: Health Status
A5: DX-CGM-G7-SEN-01 | B5: DE - MedSupply GmbH (Tier 1) | C5: =Price_Book_Master!H5 | D5: =C5*Price_Book_Master!I5 | E5: =C5*0.035 | F5: =C5*0.015 | G5: =C5*0.010 | H5: 1.8 | I5: =C5-D5-E5-F5-G5-H5 | J5: 14.5 | K5: =I5-J5 | L5: =K5/I5 | M5: =IF(L5>0.6,"Optimal",IF(L5>0.5,"Acceptable","Review"))
A6: DX-CGM-G7-SEN-01 | B6: DE - D2C Webstore Direct | C6: =Price_Book_Master!H6 | D6: 0 | E6: 0 | F6: 0 | G6: =C6*0.022 | H6: 3.2 | I6: =C6-D6-E6-F6-G6-H6 | J6: 14.5 | K6: =I6-J6 | L6: =K6/I6 | M6: =IF(L6>0.6,"Optimal",IF(L6>0.5,"Acceptable","Review"))
A7: DX-CGM-G7-SEN-01 | B7: UK - MediCare Alliance | C7: =Price_Book_Master!H7 | D7: =C7*Price_Book_Master!I7 | E7: =C7*0.040 | F7: =C7*0.010 | G7: =C7*0.010 | H7: 2.1 | I7: =C7-D7-E7-F7-G7-H7 | J7: 14.5 | K7: =I7-J7 | L7: =K7/I7 | M7: =IF(L7>0.6,"Optimal",IF(L7>0.5,"Acceptable","Review"))
A8: DX-CGM-G7-SEN-01 | B8: FR - Assistance Publique (Tender) | C8: =Price_Book_Master!H8 | D8: =C8*Price_Book_Master!I8 | E8: =C8*0.020 | F8: 0 | G8: 0 | H8: 2.5 | I8: =C8-D8-E8-F8-G8-H8 | J8: 14.5 | K8: =I8-J8 | L8: =K8/I8 | M8: =IF(L8>0.6,"Optimal",IF(L8>0.5,"Acceptable","Review"))
A9: DX-CGM-G7-SEN-01 | B9: SE - NordicHealth AB | C9: =Price_Book_Master!H9 | D9: =C9*Price_Book_Master!I9 | E9: =C9*0.030 | F9: =C9*0.020 | G9: =C9*0.010 | H9: 2.2 | I9: =C9-D9-E9-F9-G9-H9 | J9: 14.5 | K9: =I9-J9 | L9: =K9/I9 | M9: =IF(L9>0.6,"Optimal",IF(L9>0.5,"Acceptable","Review"))
A10: DX-CGM-G7-SEN-01 | B10: LT - BalticPharma UAB | C10: =Price_Book_Master!H10 | D10: =C10*Price_Book_Master!I10 | E10: =C10*0.025 | F10: =C10*0.010 | G10: =C10*0.010 | H10: 1.5 | I10: =C10-D10-E10-F10-G10-H10 | J10: 14.5 | K10: =I10-J10 | L10: =K10/I10 | M10: =IF(L10>0.6,"Optimal",IF(L10>0.5,"Acceptable","Review"))
A11: DX-CGM-G7-TRN-01 | B11: DE - MedSupply GmbH (Transmitter) | C11: =Price_Book_Master!H11 | D11: =C11*Price_Book_Master!I11 | E11: =C11*0.030 | F11: =C11*0.015 | G11: =C11*0.010 | H11: 3.5 | I11: =C11-D11-E11-F11-G11-H11 | J11: 28 | K11: =I11-J11 | L11: =K11/I11 | M11: =IF(L11>0.6,"Optimal",IF(L11>0.5,"Acceptable","Review"))
A12: DX-CGM-G7-TRN-01 | B12: UK - D2C Webstore Direct | C12: =Price_Book_Master!H12 | D12: 0 | E12: 0 | F12: 0 | G12: =C12*0.020 | H12: 4.1 | I12: =C12-D12-E12-F12-G12-H12 | J12: 28 | K12: =I12-J12 | L12: =K12/I12 | M12: =IF(L12>0.6,"Optimal",IF(L12>0.5,"Acceptable","Review"))
A13: DX-CGM-G6-SEN-03 | B13: FR - Sanofi Distribution | C13: =Price_Book_Master!H13 | D13: =C13*Price_Book_Master!I13 | E13: =C13*0.020 | F13: =C13*0.010 | G13: =C13*0.010 | H13: 3.8 | I13: =C13-D13-E13-F13-G13-H13 | J13: 38 | K13: =I13-J13 | L13: =K13/I13 | M13: =IF(L13>0.6,"Optimal",IF(L13>0.5,"Acceptable","Review"))
A14: DX-CGM-APP-SUB-01 | B14: EMEA - Hospital Clinical Portal | C14: =Price_Book_Master!H14 | D14: =C14*Price_Book_Master!I14 | E14: 0 | F14: 0 | G14: 0 | H14: 0 | I14: =C14-D14-E14-F14-G14-H14 | J14: 25 | K14: =I14-J14 | L14: =K14/I14 | M14: =IF(L14>0.6,"Optimal",IF(L14>0.5,"Acceptable","Review"))
A15: EMEA Weighted Average | C15: =AVERAGE(C5:C14) | D15: =AVERAGE(D5:D14) | E15: =AVERAGE(E5:E14) | F15: =AVERAGE(F5:F14) | G15: =AVERAGE(G5:G14) | H15: =AVERAGE(H5:H14) | I15: =AVERAGE(I5:I14) | J15: =AVERAGE(J5:J14) | K15: =AVERAGE(K5:K14) | L15: =K15/I15 | M15: HEALTHY

Sheet Sensitivity_and_Elasticity
A1: ECONOMETRIC PRICE ELASTICITY & TWO-WAY SENSITIVITY MATRIX
A2: Simulating Gross Profit Impact across Price Change % vs Elasticity Coefficients (-0.80 to -1.80)
A4: Baseline Model Parameters | D4: 2-WAY SENSITIVITY: PROJECTED GROSS PROFIT (€M) UNDER ELASTICITY
A5: Baseline EMEA Annual Units Sold: | B5: 750000 | D5: Price \ PED | E5: -0.8 | F5: -1 | G5: -1.25 | H5: -1.5 | I5: -1.8
A6: Baseline Blended Net ASP (€): | B6: 42 | D6: -0.1 | E6: =($B$5 * (1 + $D6 * E$5) * (($B$6 * (1 + $D6)) - $B$7)) / 1000000 | F6: =($B$5 * (1 + $D6 * F$5) * (($B$6 * (1 + $D6)) - $B$7)) / 1000000 | G6: =($B$5 * (1 + $D6 * G$5) * (($B$6 * (1 + $D6)) - $B$7)) / 1000000 | H6: =($B$5 * (1 + $D6 * H$5) * (($B$6 * (1 + $D6)) - $B$7)) / 1000000 | I6: =($B$5 * (1 + $D6 * I$5) * (($B$6 * (1 + $D6)) - $B$7)) / 1000000
A7: Baseline Variable Unit COGS (€): | B7: 14.5 | D7: -0.05 | E7: =($B$5 * (1 + $D7 * E$5) * (($B$6 * (1 + $D7)) - $B$7)) / 1000000 | F7: =($B$5 * (1 + $D7 * F$5) * (($B$6 * (1 + $D7)) - $B$7)) / 1000000 | G7: =($B$5 * (1 + $D7 * G$5) * (($B$6 * (1 + $D7)) - $B$7)) / 1000000 | H7: =($B$5 * (1 + $D7 * H$5) * (($B$6 * (1 + $D7)) - $B$7)) / 1000000 | I7: =($B$5 * (1 + $D7 * I$5) * (($B$6 * (1 + $D7)) - $B$7)) / 1000000
A8: Baseline Unit Contribution (€): | B8: =B6-B7 | D8: 0 | E8: =($B$5 * (1 + $D8 * E$5) * (($B$6 * (1 + $D8)) - $B$7)) / 1000000 | F8: =($B$5 * (1 + $D8 * F$5) * (($B$6 * (1 + $D8)) - $B$7)) / 1000000 | G8: =($B$5 * (1 + $D8 * G$5) * (($B$6 * (1 + $D8)) - $B$7)) / 1000000 | H8: =($B$5 * (1 + $D8 * H$5) * (($B$6 * (1 + $D8)) - $B$7)) / 1000000 | I8: =($B$5 * (1 + $D8 * I$5) * (($B$6 * (1 + $D8)) - $B$7)) / 1000000
A9: Baseline Total Gross Profit (€M): | B9: =(B5*B8)/1000000 | D9: 0.05 | E9: =($B$5 * (1 + $D9 * E$5) * (($B$6 * (1 + $D9)) - $B$7)) / 1000000 | F9: =($B$5 * (1 + $D9 * F$5) * (($B$6 * (1 + $D9)) - $B$7)) / 1000000 | G9: =($B$5 * (1 + $D9 * G$5) * (($B$6 * (1 + $D9)) - $B$7)) / 1000000 | H9: =($B$5 * (1 + $D9 * H$5) * (($B$6 * (1 + $D9)) - $B$7)) / 1000000 | I9: =($B$5 * (1 + $D9 * I$5) * (($B$6 * (1 + $D9)) - $B$7)) / 1000000
D10: 0.1 | E10: =($B$5 * (1 + $D10 * E$5) * (($B$6 * (1 + $D10)) - $B$7)) / 1000000 | F10: =($B$5 * (1 + $D10 * F$5) * (($B$6 * (1 + $D10)) - $B$7)) / 1000000 | G10: =($B$5 * (1 + $D10 * G$5) * (($B$6 * (1 + $D10)) - $B$7)) / 1000000 | H10: =($B$5 * (1 + $D10 * H$5) * (($B$6 * (1 + $D10)) - $B$7)) / 1000000 | I10: =($B$5 * (1 + $D10 * I$5) * (($B$6 * (1 + $D10)) - $B$7)) / 1000000

Sheet Jira_SFDC_Change_Governance
A1: JIRA IT & SFDC PRICE BOOK OPERATIONAL CHANGE LOG
A2: Cross-Functional Collaboration: Commercial Requests, IT Sprint Backlog, UAT Validation & Deployment
A4: Jira Ticket ID | B4: Commercial Initiative | C4: Market / Territory | D4: Change Type | E4: Requestor | F4: Legal / Compliance Signoff | G4: Finance Signoff | H4: IT Sprint Release | I4: SFDC Deployment Status | J4: Post-Deploy QA Audit
A5: JIRA-PRC-1042 | B5: G7 Launch Germany Commercial Price Book | C5: Germany (DE) | D5: New SKU Activation | E5: H. Schmidt (Commercial Lead) | F5: Approved (14/09/2026) | G5: Approved (16/09/2026) | H5: Sprint 2026.4 | I5: Production Deployed | J5: Verified 0 Schema Errors
A6: JIRA-PRC-1045 | B6: UK NHS Tender Framework Update | C6: United Kingdom (UK) | D6: Tender Price Banding | E6: E. Taylor (UK Market Dir) | F6: Approved (18/09/2026) | G6: Approved (19/09/2026) | H6: Sprint 2026.4 | I6: Production Deployed | J6: Verified 100% Price Match
A7: JIRA-PRC-1048 | B7: French Reimbursement Code Alignment | C7: France (FR) | D7: Reimbursement Index | E7: J. Moreau (Pricing Mgr) | F7: Approved (22/09/2026) | G7: Approved (24/09/2026) | H7: Sprint 2026.5 | I7: Production Deployed | J7: Passed Margin Gate
A8: JIRA-PRC-1050 | B8: Nordic SEK FX Depreciation Surcharge | C8: Sweden (SE) | D8: FX Corridor Realignment | E8: L. Lindqvist (Nordic Sales) | F8: Approved (25/09/2026) | G8: Approved (27/09/2026) | H8: Sprint 2026.5 | I8: Production Deployed | J8: Re-hedged at 0.086 EUR
A9: JIRA-PRC-1052 | B9: Baltic Distributor Margin Tier Restructure | C9: Baltics (LT/LV/EE) | D9: Tier Discount Rebate | E9: M. Kazlauskas (Baltic Reg) | F9: Approved (02/10/2026) | G9: Approved (04/10/2026) | H9: Sprint 2026.6 | I9: Production Deployed | J9: Distributor Portal Synced
A10: JIRA-PRC-1055 | B10: G7 Rechargeable Transmitter Bundle | C10: Pan-EMEA | D10: Bundle Pricing Logic | E10: C. Weber (Product Ops) | F10: Approved (08/10/2026) | G10: Approved (10/10/2026) | H10: Sprint 2026.6 | I10: Production Deployed | J10: Passed Bundle Validation
A11: JIRA-PRC-1060 | B11: G6 Legacy End-of-Life Price Adjust | C11: France (FR) | D11: Discontinuation Discount | E11: A. Dubois (Supply Chain) | F11: Approved (12/10/2026) | G11: Approved (13/10/2026) | H11: Sprint 2026.7 | I11: Production Deployed | J11: Inventory Cleared 94%
A12: JIRA-PRC-1062 | B12: Clarity Clinic SaaS Annual Subscription | C12: EMEA Regional | D12: SaaS Pricing Catalog | E12: S. Jensen (Digital Health) | F12: Approved (15/10/2026) | G12: Approved (16/10/2026) | H12: Sprint 2026.7 | I12: Production Deployed | J12: Recurring Billing Active
